[1,["5e2h+qWNxAWrpjL0ehnXJI","9bf+s7p85CU5lNzJvnAhJb","0b2Y15FTFEP6+HKTCftMwh","47SiJOKF5CJ5eKQJ8SmTgI","2fWwFJW9lGC4x5jBhXYkcY","062vpRR1xOGpIBAXRBg3jz","f3ywgvIXZOI6EdFq7engct","6aiOOQO3NAPaACIiSY8G6X","40by1893BKKJr7a6JU+RAz"],["_textureSetter"],["cc.Texture2D","cc.SpriteFrame",["cc.AudioClip",["_name","_native","duration"],0],["cc.JsonAsset",["_name","json"],1]],[[2,0,1,2,4],[3,0,1,3]],[[["1,9729,9729,33071,33071,0,0,1",-1],[0],0,[],[],[]],[["1,9729,9729,33071,33071,0,0,1",-1],[0],0,[],[],[]],[[[0,"sweet",".mp3",0.744],-1],0,0,[],[],[]],[[{"name":"image_20_2","rect":[0,0,845,695],"offset":[0,0],"originalSize":[845,695],"capInsets":[0,0,0,0]}],[1],0,[0],[0],[0]],[[[0,"feelings",".mp3",0.768],-1],0,0,[],[],[]],[[[1,"en3101",{"rows":[["tag","1","Description","image_20_1.jpg","feelings","280.-1520","feelings.mp3","happy","223.-1010","happy.mp3","sad","219.-520","sad.mp3","angry","1304.-1294","angry.mp3","surprised","1321.-829","surprised.mp3"],["tag","1","Description","image_20_2.jpg","feelings","280.-1520","feelings.mp3","scared","219.-520","scared.mp3","sad","1321.-829","sad.mp3","excited","223.-1010","excited.mp3","sleepy","1304.-1294","sleepy.mp3"],["tag","1","Description","image_20_4.jpg","taste","280.-1520","taste.mp3","hot","1333.-1350","hot.mp3","cool","284.-1307","cool.mp3","sweet","243.-839","sweet.mp3","sour","1210.-926","sour.mp3"],["tag","1","Description","image_13_4.jpg","colors","719.-1520","colors.mp3","black","1155.-1147","black.mp3","white","628.-631","white.mp3","purple","408.-1147","purple.mp3","orange","1257.-528","orange.mp3"],["quizliteracy","1","Description","image_sentence","happy","sad","scared","happy","happy.png","","happy.mp3"],["quizliteracy","1","Description","image_sentence","sad","sad","scared","happy","l5_shesad.png","","sad.mp3"],["quizliteracy","1","Description","image_sentence","black","white","black","purple","black.png","","black.mp3"],["quizliteracy","1","Description","image_word","white","black","white","purple","white.png"],["quizliteracy","1","Description","image_word","purple","purple","orange","white","purple.png"]]}]],0,0,[],[],[]],[[[0,"scared",".mp3",0.936],-1],0,0,[],[],[]],[[{"name":"black","rect":[0,0,382,322],"offset":[0,0],"originalSize":[382,322],"capInsets":[0,0,0,0]}],[1],0,[0],[0],[1]],[[[0,"cool",".mp3",0.648],-1],0,0,[],[],[]],[[[0,"surprised",".mp3",0.936],-1],0,0,[],[],[]],[["0,9729,9729,33071,33071,0,0,1",-1],[0],0,[],[],[]],[[[0,"orange",".mp3",0.624],-1],0,0,[],[],[]],[["0,9729,9729,33071,33071,0,0,1",-1],[0],0,[],[],[]],[["0,9729,9729,33071,33071,0,0,1",-1],[0],0,[],[],[]],[[[0,"happy",".mp3",0.648],-1],0,0,[],[],[]],[["1,9729,9729,33071,33071,0,0,1",-1],[0],0,[],[],[]],[["0,9729,9729,33071,33071,0,0,1",-1],[0],0,[],[],[]],[[[0,"sour",".mp3",0.768],-1],0,0,[],[],[]],[[[0,"taste",".mp3",0.72],-1],0,0,[],[],[]],[[[0,"purple",".mp3",0.672],-1],0,0,[],[],[]],[[{"name":"image_20_1","rect":[0,0,845,695],"offset":[0,0],"originalSize":[845,695],"capInsets":[0,0,0,0]}],[1],0,[0],[0],[2]],[[[0,"sleepy",".mp3",0.936],-1],0,0,[],[],[]],[[[0,"sad",".mp3",0.648],-1],0,0,[],[],[]],[[[0,"colors",".mp3",0.768],-1],0,0,[],[],[]],[[[0,"excited",".mp3",0.936],-1],0,0,[],[],[]],[[[0,"black",".mp3",0.576],-1],0,0,[],[],[]],[["0,9729,9729,33071,33071,0,0,1",-1],[0],0,[],[],[]],[[{"name":"happy","rect":[0,0,630,592],"offset":[0,0],"originalSize":[630,592],"capInsets":[0,0,0,0]}],[1],0,[0],[0],[3]],[[{"name":"purple","rect":[0,0,400,333],"offset":[0,0],"originalSize":[400,333],"capInsets":[0,0,0,0]}],[1],0,[0],[0],[4]],[[{"name":"image_20_4","rect":[0,0,845,695],"offset":[0,0],"originalSize":[845,695],"capInsets":[0,0,0,0]}],[1],0,[0],[0],[5]],[[{"name":"image_13_4","rect":[0,0,845,695],"offset":[0,0],"originalSize":[845,695],"capInsets":[0,0,0,0]}],[1],0,[0],[0],[6]],[[[0,"angry",".mp3",0.672],-1],0,0,[],[],[]],[[{"name":"l5_shesad","rect":[0,0,868,689],"offset":[0,0],"originalSize":[868,689],"capInsets":[0,0,0,0]}],[1],0,[0],[0],[7]],[[[0,"hot",".mp3",0.336],-1],0,0,[],[],[]],[["1,9729,9729,33071,33071,0,0,1",-1],[0],0,[],[],[]],[[{"name":"white","rect":[0,0,322,382],"offset":[0,0],"originalSize":[322,382],"capInsets":[0,0,0,0]}],[1],0,[0],[0],[8]],[[[0,"white",".mp3",0.624],-1],0,0,[],[],[]]]]