[1,["f7IRVS9shGk5GfMBcFBH6P","6ccYAOGLhEar2kXUuKVPXZ","d2eCn9zAlKwa1bxs7R+6C/","f51HY7YUFIBatqbDfqAivo","9bXq2etYVHvYRaIjK5RfUZ","96niuQ855DAKoPxoO2lLdP","d7pQs8WbdCYbNVsIxeUHYs","24JHsyEy1PSaT9Twptwxuw","bcWDCiTgFGW6YDRds5NpHJ","8e/cqTv4FLJJllREQZLziZ","18GD2Dw8xH4ZTtv9g7KIZ5"],["_textureSetter"],["cc.Texture2D","cc.SpriteFrame",["cc.JsonAsset",["_name","json"],1],["cc.AudioClip",["_name","_native","duration"],0]],[[3,0,1,2,4],[2,0,1,3]],[[[[1,"kn0305",{"rows":[["rocket","1","Description","ಲವಣ","ಲ,ವ,ಣ","ಲ,ವ,ಣ","ಲವಣ.mp3","salt.png","False","False"],["spelldoor","1","Description","ಅಗಲ","ಅಗ*","0","0","wide.png","ಅಗಲ.mp3"],["rocket","1","Description","ಈಚಲ","ಈ,ಚ,ಲ","ಈ,ಚ,ಲ","ಈಚಲ.mp3","palm tree.png","False","False"],["spelldoor","1","Description","ಊಟ","*ಟ","0","0","meal.png","ಊಟ.mp3"],["rocket","1","Description","ಕಡಗ","ಕ,ಡ,ಗ","ಕ,ಡ,ಗ","ಕಡಗ.mp3","bracelet.png","False","False"],["spelldoor","1","Description","ಕದ","ಕ*","0","0","door.png","ಕದ.mp3"],["rocket","1","Description","ಕರ","ಕ,ರ","ಕ,ರ","ಕರ.mp3","hand.png","False","False"],["spelldoor","1","Description","ಕಟಕ","*ಟಕ","0","0","crab.png","ಕಟಕ.mp3"],["rocket","1","Description","ಕರಟ","ಕ,ರ,ಟ","ಕ,ರ,ಟ","ಕರಟ.mp3","coconutshell.png","False","False"],["spelldoor","1","Description","ಕಮಲ","ಕಮ*","0","0","lotus.png","ಕಮಲ.mp3"],["rocket","1","Description","ಕರಗ","ಕ,ರ,ಗ","ಕ,ರ,ಗ","ಕರಗ.mp3","karagafestival.png","False","False"]]}]],0,0,[],[],[]],[[[0,"ಅಗಲ",".mp3",1.176],-1],0,0,[],[],[]],[["0,9729,9729,33071,33071,0,0,1",-1],[0],0,[],[],[]],[["0,9729,9729,33071,33071,0,0,1",-1],[0],0,[],[],[]],[[{"name":"palm tree","rect":[0,0,500,667],"offset":[0,0],"originalSize":[500,667],"capInsets":[0,0,0,0]}],[1],0,[0],[0],[0]],[[{"name":"crab","rect":[0,0,500,625],"offset":[0,0],"originalSize":[500,625],"capInsets":[0,0,0,0]}],[1],0,[0],[0],[1]],[[[0,"ಕಮಲ",".mp3",0.72],-1],0,0,[],[],[]],[[{"name":"door","rect":[0,0,868,1300],"offset":[0,0],"originalSize":[868,1300],"capInsets":[0,0,0,0]}],[1],0,[0],[0],[2]],[[{"name":"bracelet","rect":[0,0,4724,3149],"offset":[0,0],"originalSize":[4724,3149],"capInsets":[0,0,0,0]}],[1],0,[0],[0],[3]],[["0,9729,9729,33071,33071,0,0,1",-1],[0],0,[],[],[]],[[{"name":"lotus","rect":[0,0,500,333],"offset":[0,0],"originalSize":[500,333],"capInsets":[0,0,0,0]}],[1],0,[0],[0],[4]],[[{"name":"wide","rect":[0,0,750,500],"offset":[0,0],"originalSize":[750,500],"capInsets":[0,0,0,0]}],[1],0,[0],[0],[5]],[[[0,"ಕಟಕ",".mp3",0.768],-1],0,0,[],[],[]],[[[0,"ಈಚಲ",".mp3",1.008],-1],0,0,[],[],[]],[[[0,"ಕಡಗ",".mp3",0.72],-1],0,0,[],[],[]],[[[0,"ಕರಗ",".mp3",0.72],-1],0,0,[],[],[]],[[[0,"ಊಟ",".mp3",1.128],-1],0,0,[],[],[]],[["0,9729,9729,33071,33071,0,0,1",-1],[0],0,[],[],[]],[["0,9729,9729,33071,33071,0,0,1",-1],[0],0,[],[],[]],[[{"name":"coconutshell","rect":[0,0,466,375],"offset":[0,0],"originalSize":[466,375],"capInsets":[0,0,0,0]}],[1],0,[0],[0],[6]],[["0,9729,9729,33071,33071,0,0,1",-1],[0],0,[],[],[]],[[[0,"ಕರ",".mp3",0.576],-1],0,0,[],[],[]],[[[0,"ಕರಟ",".mp3",0.72],-1],0,0,[],[],[]],[[[0,"ಲವಣ",".mp3",0.72],-1],0,0,[],[],[]],[[{"name":"karagafestival","rect":[0,0,3888,2592],"offset":[0,0],"originalSize":[3888,2592],"capInsets":[0,0,0,0]}],[1],0,[0],[0],[7]],[[{"name":"salt","rect":[0,0,4480,6720],"offset":[0,0],"originalSize":[4480,6720],"capInsets":[0,0,0,0]}],[1],0,[0],[0],[8]],[["0,9729,9729,33071,33071,0,0,1",-1],[0],0,[],[],[]],[["0,9729,9729,33071,33071,0,0,1",-1],[0],0,[],[],[]],[[{"name":"meal","rect":[0,0,3025,4032],"offset":[0,0],"originalSize":[3025,4032],"capInsets":[0,0,0,0]}],[1],0,[0],[0],[9]],[["0,9729,9729,33071,33071,0,0,1",-1],[0],0,[],[],[]],[[[0,"ಕದ",".mp3",0.624],-1],0,0,[],[],[]],[["0,9729,9729,33071,33071,0,0,1",-1],[0],0,[],[],[]],[["0,9729,9729,33071,33071,0,0,1",-1],[0],0,[],[],[]],[[{"name":"hand","rect":[0,0,4000,6000],"offset":[0,0],"originalSize":[4000,6000],"capInsets":[0,0,0,0]}],[1],0,[0],[0],[10]]]]